dingo_enets/__init__.py
dingo_enets/download_models.py
dingo_enets/embedding_networks.py
dingo_enets/utils.py
dingo_enets-0.1.0.dist-info/LICENSE
dingo_enets-0.1.0.dist-info/METADATA
dingo_enets-0.1.0.dist-info/WHEEL
dingo_enets-0.1.0.dist-info/top_level.txt
dingo_enets-0.1.0.dist-info/RECORD
