Metadata-Version: 2.1
Name: dingo-enets
Version: 0.1.0
Summary: Neural networks for feature extraction for gravitational waves.
Home-page: https://github.com/max-dax/dingo-enets/
Author: Maximilian Dax
License: MIT
Platform: UNKNOWN
Requires-Python: >=3.6
License-File: LICENSE
Requires-Dist: numpy
Requires-Dist: torch
Requires-Dist: nflows
Requires-Dist: pyyaml
Requires-Dist: gdown
Requires-Dist: textwrap3
Provides-Extra: dev
Requires-Dist: pytest ; extra == 'dev'
Requires-Dist: black ; extra == 'dev'
